[
  {
    "userId": 1,
    "businessId": 8,
    "caption": "This is my dinner."
  },
  {
    "userId": 1,
    "businessId": 2
  },
  {
    "userId": 26,
    "businessId": 1,
    "caption": "Geekin' out"
  },
  {
    "userId": 21,
    "businessId": 14
  },
  {
    "userId": 28,
    "businessId": 18,
    "caption": "Sticky Hands"
  },
  {
    "userId": 21,
    "businessId": 9,
    "caption": "Popcorn!"
  },
  {
    "userId": 26,
    "businessId": 8
  },
  {
    "userId": 25,
    "businessId": 18,
    "caption": "Big fermentor"
  },
  {

    "userId": 20,
    "businessId": 2
  },
  {

    "userId": 6,
    "businessId": 15,
    "caption": "Cake!"
  }
]
